connoisseur/__init__.py
connoisseur/__main__.py
connoisseur/checkers.py
connoisseur/copy.py
connoisseur/main.py
connoisseur/modifyfilesystem.py
connoisseur/tidy.py
connoisseur/utils.py
connoisseur-0.2.0.dist-info/LICENSE
connoisseur-0.2.0.dist-info/METADATA
connoisseur-0.2.0.dist-info/WHEEL
connoisseur-0.2.0.dist-info/entry_points.txt
connoisseur-0.2.0.dist-info/top_level.txt
connoisseur-0.2.0.dist-info/RECORD
