Metadata-Version: 2.1
Name: connoisseur
Version: 0.2.0
Summary: A utility for selective copying and deletion of complex directory structures
Home-page: https://github.com/phil-arh/connoisseur.py
Author: Phil Howe
Author-email: phil.a.r.howe@gmail.com
License: GPLv3
Keywords: copy delete gitignore dockerignore docker
Platform: UNKNOWN
Requires-Dist: gitignore-parser
Requires-Dist: debugprint
